Workbook

Sheet Pivot_Analysis
A1: Customer Segment Comparison
A3: engagement_segment | B3: Count of customer_id
A4: High | B4: 755
A5: Low | B5: 7
A6: Moderate | B6: 410
A7: Very High | B7: 28
A8: Grand Total | B8: 1200
G15: Transaction Activity by Type
A20: transaction_type | B20: Count of transaction_id | C20: Average of amount
A21: Bill Payment | B21: 3467 | C21: 3290.5287
A22: Cash Withdrawal | B22: 2388 | C22: 3751.3917
A23: Credit | B23: 4419 | C23: 3508.4048
A24: Debit | B24: 7461 | C24: 3623.2945
A25: Transfer | B25: 4088 | C25: 3362.8265
A26: Grand Total | B26: 21823 | C26: 3512.401

Sheet Customer_Data
A1: customer_id | B1: age_band | C1: region | D1: relationship_years | E1: account_count | F1: account_type_count | G1: account_types | H1: transaction_count | I1: total_transaction_amount | J1: average_transaction_amount | K1: branch_visits | L1: atm_usage | M1: mobile_usage | N1: internet_usage | O1: branch_visits_was_missing | P1: atm_usage_was_missing | Q1: mobile_usage_was_missing | R1: internet_usage_was_missing | S1: service_request_count | T1: complaint_count | U1: unresolved_request_count | V1: channel_diversity | W1: total_channel_usage | X1: engagement_segment | Y1: has_complaint | Z1: has_unresolved_request | AA1: last_transaction_date | AB1: days_since_last_transaction | AC1: activity_change | AD1: declining_activity_flag
A2: CUST00001 | B2: 36-45 | C2: South | D2: 17 | E2: 1 | F2: 1 | G2: Savings | H2: 17 | I2: 38691.18 | J2: 2275.9517647058824 | K2: 2 | L2: 6 | M2: 10 | N2: 8 | O2: 0 | P2: 0 | Q2: 0 | R2: 0 | S2: 1 | T2: 0 | U2: 0 | V2: 4 | W2: 26 | X2: High | Y2: 0 | Z2: 0 | AA2: 45942 | AB2: 81 | AC2: -9 | AD2: 1
A3: CUST00002 | B3: 46-60 | C3: West | D3: 2 | E3: 1 | F3: 1 | G3: Savings | H3: 16 | I3: 29347.55 | J3: 1834.2219 | K3: 1 | L3: 5 | M3: 9 | N3: 8 | O3: 0 | P3: 0 | Q3: 0 | R3: 0 | S3: 1 | T3: 0 | U3: 0 | V3: 4 | W3: 23 | X3: High | Y3: 0 | Z3: 0 | AA3: 46016 | AB3: 7 | AC3: -2 | AD3: 1
A4: CUST00003 | B4: 60+ | C4: Central | D4: 23 | E4: 1 | F4: 1 | G4: Savings | H4: 10 | I4: 19452.99 | J4: 1945.2990000000002 | K4: 5 | L4: 9 | M4: 12 | N4: 5 | O4: 0 | P4: 0 | Q4: 0 | R4: 0 | S4: 1 | T4: 1 | U4: 0 | V4: 4 | W4: 31 | X4: Moderate | Y4: 1 | Z4: 0 | AA4: 46013 | AB4: 10 | AC4: -4 | AD4: 1
A5: CUST00004 | B5: 60+ | C5: West | D5: 10 | E5: 1 | F5: 1 | G5: Current | H5: 12 | I5: 26822.23 | J5: 2235.1858333333334 | K5: 2 | L5: 4 | M5: 8 | N5: 4 | O5: 0 | P5: 0 | Q5: 0 | R5: 0 | S5: 2 | T5: 1 | U5: 0 | V5: 4 | W5: 18 | X5: Moderate | Y5: 1 | Z5: 0 | AA5: 46006 | AB5: 17 | AC5: 2 | AD5: 0
A6: CUST00005 | B6: 26-35 | C6: West | D6: 4 | E6: 1 | F6: 1 | G6: Current | H6: 24 | I6: 65388.56 | J6: 2724.523333333333 | K6: 3 | L6: 7 | M6: 5 | N6: 7 | O6: 0 | P6: 0 | Q6: 0 | R6: 0 | S6: 1 | T6: 0 | U6: 0 | V6: 4 | W6: 22 | X6: High | Y6: 0 | Z6: 0 | AA6: 45947 | AB6: 76 | AC6: -10 | AD6: 1
A7: CUST00006 | B7: 36-45 | C7: East | D7: 8 | E7: 3 | F7: 2 | G7: Salary, Savings | H7: 18 | I7: 46448.46 | J7: 2580.47 | K7: 1 | L7: 5 | M7: 17 | N7: 3 | O7: 0 | P7: 0 | Q7: 0 | R7: 0 | S7: 2 | T7: 2 | U7: 0 | V7: 4 | W7: 26 | X7: High | Y7: 1 | Z7: 0 | AA7: 45998 | AB7: 25 | AC7: 0 | AD7: 0
A8: CUST00007 | B8: 26-35 | C8: North | D8: 10 | E8: 1 | F8: 1 | G8: Salary | H8: 23 | I8: 81250.41 | J8: 3532.6265217391306 | K8: 2 | L8: 3 | M8: 17 | N8: 6 | O8: 0 | P8: 0 | Q8: 0 | R8: 0 | S8: 0 | T8: 0 | U8: 0 | V8: 4 | W8: 28 | X8: High | Y8: 0 | Z8: 0 | AA8: 46014 | AB8: 9 | AC8: 7 | AD8: 0
A9: CUST00008 | B9: 46-60 | C9: West | D9: 12 | E9: 2 | F9: 2 | G9: Current, Fixed Deposit | H9: 20 | I9: 106335.73 | J9: 5316.7865 | K9: 2 | L9: 5 | M9: 11 | N9: 5 | O9: 0 | P9: 0 | Q9: 0 | R9: 0 | S9: 1 | T9: 0 | U9: 0 | V9: 4 | W9: 23 | X9: High | Y9: 0 | Z9: 0 | AA9: 46020 | AB9: 3 | AC9: -4 | AD9: 1
A10: CUST00009 | B10: 36-45 | C10: Central | D10: 4 | E10: 1 | F10: 1 | G10: Savings | H10: 11 | I10: 51319.19 | J10: 4665.380909090909 | K10: 2 | L10: 5 | M10: 3 | N10: 11 | O10: 0 | P10: 0 | Q10: 0 | R10: 0 | S10: 0 | T10: 0 | U10: 0 | V10: 4 | W10: 21 | X10: Moderate | Y10: 0 | Z10: 0 | AA10: 45988 | AB10: 35 | AC10: 3 | AD10: 0
A11: CUST00010 | B11: 36-45 | C11: South | D11: 8 | E11: 2 | F11: 1 | G11: Savings | H11: 7 | I11: 14222.92 | J11: 2031.8457142857144 | K11: 2 | L11: 3 | M11: 9 | N11: 5 | O11: 1 | P11: 0 | Q11: 0 | R11: 0 | S11: 2 | T11: 1 | U11: 0 | V11: 4 | W11: 19 | X11: Moderate | Y11: 1 | Z11: 0 | AA11: 45939 | AB11: 84 | AC11: -3 | AD11: 1
A12: CUST00011 | B12: 26-35 | C12: Central | D12: 22 | E12: 1 | F12: 1 | G12: Fixed Deposit | H12: 28 | I12: 158418.95 | J12: 5657.819642857144 | K12: 1 | L12: 7 | M12: 11 | N12: 7 | O12: 0 | P12: 0 | Q12: 1 | R12: 0 | S12: 0 | T12: 0 | U12: 0 | V12: 4 | W12: 26 | X12: High | Y12: 0 | Z12: 0 | AA12: 45980 | AB12: 43 | AC12: -4 | AD12: 1
A13: CUST00012 | B13: 46-60 | C13: Central | D13: 2 | E13: 1 | F13: 1 | G13: Savings | H13: 24 | I13: 150229.66 | J13: 6259.569166666667 | K13: 3 | L13: 4 | M13: 9 | N13: 4 | O13: 0 | P13: 0 | Q13: 0 | R13: 0 | S13: 1 | T13: 0 | U13: 0 | V13: 4 | W13: 20 | X13: High | Y13: 0 | Z13: 0 | AA13: 46016 | AB13: 7 | AC13: 2 | AD13: 0
A14: CUST00013 | B14: 18-25 | C14: Central | D14: 14 | E14: 1 | F14: 1 | G14: Fixed Deposit | H14: 12 | I14: 38751.770000000004 | J14: 3229.314166666667 | K14: 0 | L14: 0 | M14: 11 | N14: 6 | O14: 0 | P14: 0 | Q14: 0 | R14: 0 | S14: 1 | T14: 0 | U14: 0 | V14: 2 | W14: 17 | X14: Moderate | Y14: 0 | Z14: 0 | AA14: 45983 | AB14: 40 | AC14: 6 | AD14: 0
A15: CUST00014 | B15: 60+ | C15: West | D15: 18 | E15: 1 | F15: 1 | G15: Savings | H15: 10 | I15: 20968.61 | J15: 2096.861 | K15: 1 | L15: 8 | M15: 11 | N15: 8 | O15: 0 | P15: 0 | Q15: 0 | R15: 0 | S15: 1 | T15: 0 | U15: 0 | V15: 4 | W15: 28 | X15: Moderate | Y15: 0 | Z15: 0 | AA15: 45986 | AB15: 37 | AC15: 0 | AD15: 0
A16: CUST00015 | B16: 36-45 | C16: West | D16: 4 | E16: 3 | F16: 2 | G16: Fixed Deposit, Savings | H16: 19 | I16: 43600.47 | J16: 2294.7615789473684 | K16: 1 | L16: 4 | M16: 9 | N16: 6 | O16: 0 | P16: 0 | Q16: 0 | R16: 0 | S16: 0 | T16: 0 | U16: 0 | V16: 4 | W16: 20 | X16: High | Y16: 0 | Z16: 0 | AA16: 45988 | AB16: 35 | AC16: 1 | AD16: 0
A17: CUST00016 | B17: 26-35 | C17: West | D17: 25 | E17: 2 | F17: 1 | G17: Savings | H17: 24 | I17: 100440.70999999999 | J17: 4185.029583333333 | K17: 0 | L17: 5 | M17: 8 | N17: 12 | O17: 0 | P17: 0 | Q17: 0 | R17: 0 | S17: 2 | T17: 0 | U17: 0 | V17: 3 | W17: 25 | X17: High | Y17: 0 | Z17: 0 | AA17: 46017 | AB17: 6 | AC17: 4 | AD17: 0
A18: CUST00017 | B18: 36-45 | C18: Central | D18: 15 | E18: 2 | F18: 1 | G18: Savings | H18: 17 | I18: 35474.92 | J18: 2086.7599999999998 | K18: 3 | L18: 4 | M18: 12 | N18: 7 | O18: 0 | P18: 0 | Q18: 0 | R18: 0 | S18: 1 | T18: 1 | U18: 1 | V18: 4 | W18: 26 | X18: High | Y18: 1 | Z18: 1 | AA18: 46014 | AB18: 9 | AC18: -5 | AD18: 1
A19: CUST00018 | B19: 46-60 | C19: West | D19: 18 | E19: 2 | F19: 2 | G19: Fixed Deposit, Savings | H19: 18 | I19: 67790.64 | J19: 3766.1466666666665 | K19: 0 | L19: 5 | M19: 19 | N19: 5 | O19: 0 | P19: 1 | Q19: 0 | R19: 0 | S19: 2 | T19: 0 | U19: 0 | V19: 3 | W19: 29 | X19: High | Y19: 0 | Z19: 0 | AA19: 45986 | AB19: 37 | AC19: -10 | AD19: 1
A20: CUST00019 | B20: 18-25 | C20: Central | D20: 13 | E20: 1 | F20: 1 | G20: Savings | H20: 16 | I20: 20839.9 | J20: 1302.4938 | K20: 1 | L20: 2 | M20: 17 | N20: 8 | O20: 0 | P20: 0 | Q20: 0 | R20: 0 | S20: 0 | T20: 0 | U20: 0 | V20: 4 | W20: 28 | X20: High | Y20: 0 | Z20: 0 | AA20: 46020 | AB20: 3 | AC20: 4 | AD20: 0
A21: CUST00020 | B21: 46-60 | C21: South | D21: 1 | E21: 1 | F21: 1 | G21: Salary | H21: 14 | I21: 42484.840000000004 | J21: 3034.631428571429 | K21: 1 | L21: 4 | M21: 6 | N21: 8 | O21: 0 | P21: 0 | Q21: 0 | R21: 0 | S21: 1 | T21: 1 | U21: 1 | V21: 4 | W21: 19 | X21: Moderate | Y21: 1 | Z21: 1 | AA21: 46013 | AB21: 10 | AC21: 8 | AD21: 0
A22: CUST00021 | B22: 36-45 | C22: West | D22: 18 | E22: 1 | F22: 1 | G22: Savings | H22: 16 | I22: 28727.58 | J22: 1795.4738 | K22: 1 | L22: 8 | M22: 11 | N22: 6 | O22: 0 | P22: 0 | Q22: 0 | R22: 0 | S22: 1 | T22: 0 | U22: 0 | V22: 4 | W22: 26 | X22: High | Y22: 0 | Z22: 0 | AA22: 46021 | AB22: 2 | AC22: 10 | AD22: 0
A23: CUST00022 | B23: 18-25 | C23: West | D23: 24 | E23: 2 | F23: 2 | G23: Fixed Deposit, Savings | H23: 11 | I23: 31398.91 | J23: 2854.4463636363635 | K23: 2 | L23: 5 | M23: 9 | N23: 8 | O23: 0 | P23: 0 | Q23: 0 | R23: 0 | S23: 1 | T23: 1 | U23: 0 | V23: 4 | W23: 24 | X23: Moderate | Y23: 1 | Z23: 0 | AA23: 46017 | AB23: 6 | AC23: 1 | AD23: 0
A24: CUST00023 | B24: 26-35 | C24: West | D24: 3 | E24: 2 | F24: 1 | G24: Savings | H24: 22 | I24: 69972.07 | J24: 3180.548636363637 | K24: 1 | L24: 4 | M24: 10 | N24: 3 | O24: 0 | P24: 0 | Q24: 0 | R24: 0 | S24: 1 | T24: 0 | U24: 0 | V24: 4 | W24: 18 | X24: High | Y24: 0 | Z24: 0 | AA24: 46017 | AB24: 6 | AC24: 0 | AD24: 0
A25: CUST00024 | B25: 36-45 | C25: South | D25: 7 | E25: 2 | F25: 2 | G25: Current, Fixed Deposit | H25: 12 | I25: 43955.75 | J25: 3662.9791666666665 | K25: 3 | L25: 5 | M25: 16 | N25: 6 | O25: 0 | P25: 0 | Q25: 0 | R25: 0 | S25: 1 | T25: 0 | U25: 0 | V25: 4 | W25: 30 | X25: Moderate | Y25: 0 | Z25: 0 | AA25: 46001 | AB25: 22 | AC25: 2 | AD25: 0
A26: CUST00025 | B26: 60+ | C26: East | D26: 5 | E26: 1 | F26: 1 | G26: Salary | H26: 13 | I26: 23760.6 | J26: 1827.7384615384615 | K26: 4 | L26: 5 | M26: 15 | N26: 8 | O26: 0 | P26: 0 | Q26: 0 | R26: 0 | S26: 4 | T26: 0 | U26: 1 | V26: 4 | W26: 32 | X26: Moderate | Y26: 0 | Z26: 1 | AA26: 45992 | AB26: 31 | AC26: 3 | AD26: 0
A27: CUST00026 | B27: 36-45 | C27: North | D27: 25 | E27: 1 | F27: 1 | G27: Savings | H27: 16 | I27: 68616.83 | J27: 4288.5519 | K27: 3 | L27: 5 | M27: 15 | N27: 5 | O27: 0 | P27: 0 | Q27: 0 | R27: 0 | S27: 1 | T27: 0 | U27: 0 | V27: 4 | W27: 28 | X27: High | Y27: 0 | Z27: 0 | AA27: 45981 | AB27: 42 | AC27: -2 | AD27: 1
A28: CUST00027 | B28: 60+ | C28: North | D28: 15 | E28: 2 | F28: 2 | G28: Salary, Savings | H28: 8 | I28: 42040.33 | J28: 5255.0413 | K28: 1 | L28: 3 | M28: 15 | N28: 6 | O28: 0 | P28: 0 | Q28: 0 | R28: 0 | S28: 0 | T28: 0 | U28: 0 | V28: 4 | W28: 25 | X28: Moderate | Y28: 0 | Z28: 0 | AA28: 46017 | AB28: 6 | AC28: 2 | AD28: 0
A29: CUST00028 | B29: 18-25 | C29: West | D29: 3 | E29: 3 | F29: 2 | G29: Fixed Deposit, Savings | H29: 10 | I29: 32507.49 | J29: 3250.7490000000003 | K29: 2 | L29: 7 | M29: 11 | N29: 7 | O29: 0 | P29: 0 | Q29: 0 | R29: 0 | S29: 2 | T29: 1 | U29: 1 | V29: 4 | W29: 27 | X29: Moderate | Y29: 1 | Z29: 1 | AA29: 46010 | AB29: 13 | AC29: -4 | AD29: 1
A30: CUST00029 | B30: 18-25 | C30: Central | D30: 2 | E30: 2 | F30: 2 | G30: Fixed Deposit, Savings | H30: 15 | I30: 63339.56 | J30: 4222.637333333333 | K30: 5 | L30: 7 | M30: 10 | N30: 7 | O30: 0 | P30: 0 | Q30: 0 | R30: 0 | S30: 1 | T30: 0 | U30: 0 | V30: 4 | W30: 29 | X30: Moderate | Y30: 0 | Z30: 0 | AA30: 45955 | AB30: 68 | AC30: -3 | AD30: 1
A31: CUST00030 | B31: 26-35 | C31: South | D31: 20 | E31: 2 | F31: 2 | G31: Salary, Savings | H31: 27 | I31: 115889.53 | J31: 4292.204814814815 | K31: 2 | L31: 5 | M31: 15 | N31: 13 | O31: 0 | P31: 0 | Q31: 0 | R31: 0 | S31: 0 | T31: 0 | U31: 0 | V31: 4 | W31: 35 | X31: High | Y31: 0 | Z31: 0 | AA31: 45961 | AB31: 62 | AC31: -3 | AD31: 1
A32: CUST00031 | B32: 26-35 | C32: East | D32: 6 | E32: 2 | F32: 2 | G32: Current, Fixed Deposit | H32: 18 | I32: 46906.34 | J32: 2605.9077777777775 | K32: 4 | L32: 4 | M32: 17 | N32: 3 | O32: 0 | P32: 0 | Q32: 0 | R32: 0 | S32: 1 | T32: 0 | U32: 0 | V32: 4 | W32: 28 | X32: High | Y32: 0 | Z32: 0 | AA32: 46003 | AB32: 20 | AC32: 6 | AD32: 0
A33: CUST00032 | B33: 26-35 | C33: East | D33: 25 | E33: 1 | F33: 1 | G33: Current | H33: 23 | I33: 155436.45 | J33: 6758.106521739131 | K33: 2 | L33: 5 | M33: 7 | N33: 11 | O33: 0 | P33: 0 | Q33: 0 | R33: 0 | S33: 1 | T33: 1 | U33: 0 | V33: 4 | W33: 25 | X33: High | Y33: 1 | Z33: 0 | AA33: 46009 | AB33: 14 | AC33: 1 | AD33: 0
A34: CUST00033 | B34: 46-60 | C34: East | D34: 9 | E34: 1 | F34: 1 | G34: Savings | H34: 15 | I34: 27144.64 | J34: 1809.6426666666666 | K34: 0 | L34: 4 | M34: 10 | N34: 7 | O34: 0 | P34: 0 | Q34: 0 | R34: 1 | S34: 2 | T34: 0 | U34: 1 | V34: 3 | W34: 21 | X34: Moderate | Y34: 0 | Z34: 1 | AA34: 46017 | AB34: 6 | AC34: -1 | AD34: 1
A35: CUST00034 | B35: 26-35 | C35: Central | D35: 19 | E35: 1 | F35: 1 | G35: Current | H35: 28 | I35: 83092.01 | J35: 2967.5717857142854 | K35: 2 | L35: 6 | M35: 12 | N35: 11 | O35: 0 | P35: 0 | Q35: 0 | R35: 0 | S35: 1 | T35: 1 | U35: 0 | V35: 4 | W35: 31 | X35: High | Y35: 1 | Z35: 0 | AA35: 46019 | AB35: 4 | AC35: 2 | AD35: 0
A36: CUST00035 | B36: 36-45 | C36: West | D36: 14 | E36: 1 | F36: 1 | G36: Savings | H36: 14 | I36: 23005.94 | J36: 1643.2814285714285 | K36: 0 | L36: 4 | M36: 10 | N36: 9 | O36: 0 | P36: 0 | Q36: 0 | R36: 0 | S36: 0 | T36: 0 | U36: 0 | V36: 3 | W36: 23 | X36: Moderate | Y36: 0 | Z36: 0 | AA36: 46016 | AB36: 7 | AC36: 0 | AD36: 0
A37: CUST00036 | B37: 26-35 | C37: Central | D37: 6 | E37: 2 | F37: 1 | G37: Savings | H37: 22 | I37: 74582.72 | J37: 3390.1236363636363 | K37: 6 | L37: 9 | M37: 6 | N37: 9 | O37: 0 | P37: 0 | Q37: 0 | R37: 0 | S37: 1 | T37: 1 | U37: 0 | V37: 4 | W37: 30 | X37: High | Y37: 1 | Z37: 0 | AA37: 46011 | AB37: 12 | AC37: -6 | AD37: 1
A38: CUST00037 | B38: 60+ | C38: West | D38: 25 | E38: 1 | F38: 1 | G38: Savings | H38: 12 | I38: 68744.93000000001 | J38: 5728.744166666667 | K38: 1 | L38: 7 | M38: 9 | N38: 12 | O38: 0 | P38: 0 | Q38: 0 | R38: 0 | S38: 0 | T38: 0 | U38: 0 | V38: 4 | W38: 29 | X38: Moderate | Y38: 0 | Z38: 0 | AA38: 46016 | AB38: 7 | AC38: -2 | AD38: 1
A39: CUST00038 | B39: 18-25 | C39: South | D39: 7 | E39: 2 | F39: 2 | G39: Fixed Deposit, Savings | H39: 15 | I39: 24312.28 | J39: 1620.8186666666666 | K39: 2 | L39: 6 | M39: 8 | N39: 15 | O39: 0 | P39: 0 | Q39: 0 | R39: 0 | S39: 3 | T39: 2 | U39: 1 | V39: 4 | W39: 31 | X39: Moderate | Y39: 1 | Z39: 1 | AA39: 46019 | AB39: 4 | AC39: 11 | AD39: 0
A40: CUST00039 | B40: 18-25 | C40: North | D40: 15 | E40: 1 | F40: 1 | G40: Savings | H40: 16 | I40: 43209.25 | J40: 2700.5781 | K40: 1 | L40: 4 | M40: 8 | N40: 5 | O40: 0 | P40: 0 | Q40: 0 | R40: 0 | S40: 1 | T40: 0 | U40: 0 | V40: 4 | W40: 18 | X40: High | Y40: 0 | Z40: 0 | AA40: 46015 | AB40: 8 | AC40: -2 | AD40: 1
A41: CUST00040 | B41: 26-35 | C41: West | D41: 25 | E41: 1 | F41: 1 | G41: Salary | H41: 25 | I41: 75624.25 | J41: 3024.97 | K41: 5 | L41: 4 | M41: 11 | N41: 5 | O41: 0 | P41: 0 | Q41: 0 | R41: 0 | S41: 1 | T41: 0 | U41: 0 | V41: 4 | W41: 25 | X41: High | Y41: 0 | Z41: 0 | AA41: 45999 | AB41: 24 | AC41: -3 | AD41: 1
A42: CUST00041 | B42: 26-35 | C42: Central | D42: 5 | E42: 2 | F42: 2 | G42: Fixed Deposit, Savings | H42: 19 | I42: 48802.69 | J42: 2568.5626315789473 | K42: 1 | L42: 5 | M42: 9 | N42: 11 | O42: 0 | P42: 0 | Q42: 0 | R42: 0 | S42: 0 | T42: 0 | U42: 0 | V42: 4 | W42: 26 | X42: High | Y42: 0 | Z42: 0 | AA42: 46017 | AB42: 6 | AC42: 1 | AD42: 0
A43: CUST00042 | B43: 46-60 | C43: West | D43: 16 | E43: 3 | F43: 2 | G43: Salary, Savings | H43: 21 | I43: 55736.659999999996 | J43: 2654.1266666666666 | K43: 2 | L43: 2 | M43: 10 | N43: 13 | O43: 0 | P43: 0 | Q43: 0 | R43: 0 | S43: 2 | T43: 1 | U43: 1 | V43: 4 | W43: 27 | X43: High | Y43: 1 | Z43: 1 | AA43: 46016 | AB43: 7 | AC43: 3 | AD43: 0
A44: CUST00043 | B44: 18-25 | C44: West | D44: 15 | E44: 2 | F44: 2 | G44: Salary, Savings | H44: 19 | I44: 37455.68 | J44: 1971.3515789473684 | K44: 1 | L44: 4 | M44: 12 | N44: 9 | O44: 0 | P44: 0 | Q44: 0 | R44: 0 | S44: 1 | T44: 1 | U44: 1 | V44: 4 | W44: 26 | X44: High | Y44: 1 | Z44: 1 | AA44: 45985 | AB44: 38 | AC44: -3 | AD44: 1
A45: CUST00044 | B45: 18-25 | C45: West | D45: 24 | E45: 3 | F45: 2 | G45: Fixed Deposit, Savings | H45: 16 | I45: 46495.92 | J45: 2905.995 | K45: 0 | L45: 7 | M45: 11 | N45: 4 | O45: 0 | P45: 0 | Q45: 0 | R45: 0 | S45: 1 | T45: 0 | U45: 0 | V45: 3 | W45: 22 | X45: High | Y45: 0 | Z45: 0 | AA45: 46016 | AB45: 7 | AC45: 4 | AD45: 0
A46: CUST00045 | B46: 60+ | C46: West | D46: 1 | E46: 1 | F46: 1 | G46: Savings | H46: 8 | I46: 24829.09 | J46: 3103.6363 | K46: 1 | L46: 5 | M46: 18 | N46: 6 | O46: 0 | P46: 0 | Q46: 0 | R46: 0 | S46: 0 | T46: 0 | U46: 0 | V46: 4 | W46: 30 | X46: Moderate | Y46: 0 | Z46: 0 | AA46: 45994 | AB46: 29 | AC46: 0 | AD46: 0
A47: CUST00046 | B47: 18-25 | C47: Central | D47: 24 | E47: 1 | F47: 1 | G47: Savings | H47: 17 | I47: 82761.53 | J47: 4868.325294117647 | K47: 2 | L47: 3 | M47: 11 | N47: 12 | O47: 0 | P47: 0 | Q47: 0 | R47: 0 | S47: 0 | T47: 0 | U47: 0 | V47: 4 | W47: 28 | X47: High | Y47: 0 | Z47: 0 | AA47: 45995 | AB47: 28 | AC47: 1 | AD47: 0
A48: CUST00047 | B48: 26-35 | C48: South | D48: 5 | E48: 1 | F48: 1 | G48: Savings | H48: 24 | I48: 114313.72 | J48: 4763.071666666667 | K48: 1 | L48: 3 | M48: 12 | N48: 9 | O48: 0 | P48: 0 | Q48: 0 | R48: 0 | S48: 1 | T48: 0 | U48: 0 | V48: 4 | W48: 25 | X48: High | Y48: 0 | Z48: 0 | AA48: 46014 | AB48: 9 | AC48: 0 | AD48: 0
A49: CUST00048 | B49: 18-25 | C49: Central | D49: 25 | E49: 1 | F49: 1 | G49: Savings | H49: 10 | I49: 39632.1 | J49: 3963.21 | K49: 5 | L49: 3 | M49: 6 | N49: 3 | O49: 0 | P49: 0 | Q49: 0 | R49: 0 | S49: 1 | T49: 0 | U49: 0 | V49: 4 | W49: 17 | X49: Moderate | Y49: 0 | Z49: 0 | AA49: 45992 | AB49: 31 | AC49: 4 | AD49: 0
A50: CUST00049 | B50: 46-60 | C50: South | D50: 3 | E50: 2 | F50: 2 | G50: Current, Salary | H50: 12 | I50: 26367.480000000003 | J50: 2197.2900000000004 | K50: 2 | L50: 4 | M50: 10 | N50: 7 | O50: 0 | P50: 0 | Q50: 0 | R50: 1 | S50: 0 | T50: 0 | U50: 0 | V50: 4 | W50: 23 | X50: Moderate | Y50: 0 | Z50: 0 | AA50: 45996 | AB50: 27 | AC50: 2 | AD50: 0
A51: CUST00050 | B51: 18-25 | C51: South | D51: 6 | E51: 2 | F51: 2 | G51: Salary, Savings | H51: 22 | I51: 82482.24 | J51: 3749.1927272727276 | K51: 1 | L51: 6 | M51: 11 | N51: 5 | O51: 0 | P51: 0 | Q51: 0 | R51: 0 | S51: 0 | T51: 0 | U51: 0 | V51: 4 | W51: 23 | X51: High | Y51: 0 | Z51: 0 | AA51: 45998 | AB51: 25 | AC51: 2 | AD51: 0
A52: CUST00051 | B52: 26-35 | C52: East | D52: 25 | E52: 2 | F52: 2 | G52: Current, Savings | H52: 23 | I52: 122853.67 | J52: 5341.463913043478 | K52: 2 | L52: 4 | M52: 8 | N52: 9 | O52: 0 | P52: 0 | Q52: 0 | R52: 0 | S52: 2 | T52: 0 | U52: 1 | V52: 4 | W52: 23 | X52: High | Y52: 0 | Z52: 1 | AA52: 45972 | AB52: 51 | AC52: 5 | AD52: 0
A53: CUST00052 | B53: 26-35 | C53: South | D53: 4 | E53: 1 | F53: 1 | G53: Current | H53: 26 | I53: 50358.75 | J53: 1936.875 | K53: 1 | L53: 6 | M53: 7 | N53: 6 | O53: 0 | P53: 0 | Q53: 0 | R53: 0 | S53: 2 | T53: 1 | U53: 0 | V53: 4 | W53: 20 | X53: High | Y53: 1 | Z53: 0 | AA53: 46009 | AB53: 14 | AC53: 4 | AD53: 0
A54: CUST00053 | B54: 18-25 | C54: West | D54: 17 | E54: 1 | F54: 1 | G54: Salary | H54: 17 | I54: 45311.08 | J54: 2665.3576470588237 | K54: 3 | L54: 4 | M54: 10 | N54: 4 | O54: 0 | P54: 0 | Q54: 0 | R54: 0 | S54: 1 | T54: 0 | U54: 0 | V54: 4 | W54: 21 | X54: High | Y54: 0 | Z54: 0 | AA54: 46012 | AB54: 11 | AC54: -1 | AD54: 1
A55: CUST00054 | B55: 60+ | C55: West | D55: 14 | E55: 1 | F55: 1 | G55: Fixed Deposit | H55: 7 | I55: 17142.64 | J55: 2448.9485714285715 | K55: 2 | L55: 3 | M55: 12 | N55: 6 | O55: 0 | P55: 0 | Q55: 0 | R55: 0 | S55: 1 | T55: 1 | U55: 0 | V55: 4 | W55: 23 | X55: Moderate | Y55: 1 | Z55: 0 | AA55: 45978 | AB55: 45 | AC55: -3 | AD55: 1
A56: CUST00055 | B56: 46-60 | C56: South | D56: 20 | E56: 1 | F56: 1 | G56: Salary | H56: 17 | I56: 42003.520000000004 | J56: 2470.7952941176472 | K56: 0 | L56: 4 | M56: 7 | N56: 13 | O56: 0 | P56: 0 | Q56: 0 | R56: 0 | S56: 2 | T56: 1 | U56: 0 | V56: 3 | W56: 24 | X56: High | Y56: 1 | Z56: 0 | AA56: 45999 | AB56: 24 | AC56: 1 | AD56: 0
A57: CUST00056 | B57: 18-25 | C57: North | D57: 24 | E57: 1 | F57: 1 | G57: Fixed Deposit | H57: 19 | I57: 41259.58 | J57: 2171.556842105263 | K57: 3 | L57: 5 | M57: 9 | N57: 8 | O57: 0 | P57: 0 | Q57: 0 | R57: 0 | S57: 1 | T57: 0 | U57: 0 | V57: 4 | W57: 25 | X57: High | Y57: 0 | Z57: 0 | AA57: 46016 | AB57: 7 | AC57: 3 | AD57: 0
A58: CUST00057 | B58: 26-35 | C58: West | D58: 21 | E58: 1 | F58: 1 | G58: Current | H58: 27 | I58: 63638.67 | J58: 2356.987777777778 | K58: 3 | L58: 3 | M58: 6 | N58: 7 | O58: 0 | P58: 0 | Q58: 0 | R58: 0 | S58: 0 | T58: 0 | U58: 0 | V58: 4 | W58: 19 | X58: High | Y58: 0 | Z58: 0 | AA58: 46020 | AB58: 3 | AC58: -3 | AD58: 1
A59: CUST00058 | B59: 26-35 | C59: West | D59: 5 | E59: 1 | F59: 1 | G59: Savings | H59: 20 | I59: 67613.06 | J59: 3380.653 | K59: 2 | L59: 6 | M59: 4 | N59: 7 | O59: 1 | P59: 0 | Q59: 0 | R59: 0 | S59: 1 | T59: 0 | U59: 0 | V59: 4 | W59: 19 | X59: High | Y59: 0 | Z59: 0 | AA59: 46007 | AB59: 16 | AC59: -6 | AD59: 1
A60: CUST00059 | B60: 60+ | C60: South | D60: 21 | E60: 1 | F60: 1 | G60: Fixed Deposit | H60: 9 | I60: 20747.28 | J60: 2305.253333333333 | K60: 2 | L60: 7 | M60: 10 | N60: 8 | O60: 0 | P60: 0 | Q60: 0 | R60: 0 | S60: 1 | T60: 0 | U60: 1 | V60: 4 | W60: 27 | X60: Moderate | Y60: 0 | Z60: 1 | AA60: 46003 | AB60: 20 | AC60: -1 | AD60: 1
A61: CUST00060 | B61: 46-60 | C61: South | D61: 15 | E61: 1 | F61: 1 | G61: Savings | H61: 17 | I61: 51866.05 | J61: 3050.944117647059 | K61: 0 | L61: 2 | M61: 7 | N61: 4 | O61: 0 | P61: 0 | Q61: 0 | R61: 0 | S61: 1 | T61: 1 | U61: 0 | V61: 3 | W61: 13 | X61: High | Y61: 1 | Z61: 0 | AA61: 46007 | AB61: 16 | AC61: 1 | AD61: 0
A62: CUST00061 | B62: 60+ | C62: South | D62: 22 | E62: 1 | F62: 1 | G62: Savings | H62: 11 | I62: 28204.36 | J62: 2564.0327272727272 | K62: 2 | L62: 3 | M62: 12 | N62: 7 | O62: 0 | P62: 0 | Q62: 0 | R62: 1 | S62: 1 | T62: 0 | U62: 0 | V62: 4 | W62: 24 | X62: Moderate | Y62: 0 | Z62: 0 | AA62: 45999 | AB62: 24 | AC62: 1 | AD62: 0
A63: CUST00062 | B63: 60+ | C63: North | D63: 1 | E63: 2 | F63: 2 | G63: Current, Savings | H63: 10 | I63: 50904.71 | J63: 5090.471 | K63: 0 | L63: 4 | M63: 15 | N63: 15 | O63: 0 | P63: 0 | Q63: 0 | R63: 0 | S63: 1 | T63: 0 | U63: 0 | V63: 3 | W63: 34 | X63: Moderate | Y63: 0 | Z63: 0 | AA63: 45967 | AB63: 56 | AC63: 2 | AD63: 0
A64: CUST00063 | B64: 26-35 | C64: South | D64: 15 | E64: 2 | F64: 2 | G64: Salary, Savings | H64: 29 | I64: 134818.65 | J64: 4648.918965517241 | K64: 4 | L64: 3 | M64: 14 | N64: 6 | O64: 0 | P64: 0 | Q64: 0 | R64: 0 | S64: 0 | T64: 0 | U64: 0 | V64: 4 | W64: 27 | X64: High | Y64: 0 | Z64: 0 | AA64: 46016 | AB64: 7 | AC64: -1 | AD64: 1
A65: CUST00064 | B65: 26-35 | C65: West | D65: 3 | E65: 1 | F65: 1 | G65: Savings | H65: 28 | I65: 79786.06 | J65: 2849.5021428571426 | K65: 5 | L65: 4 | M65: 13 | N65: 10 | O65: 0 | P65: 0 | Q65: 0 | R65: 0 | S65: 2 | T65: 0 | U65: 0 | V65: 4 | W65: 32 | X65: High | Y65: 0 | Z65: 0 | AA65: 46010 | AB65: 13 | AC65: -6 | AD65: 1
A66: CUST00065 | B66: 26-35 | C66: West | D66: 9 | E66: 1 | F66: 1 | G66: Savings | H66: 24 | I66: 101439.59 | J66: 4226.649583333333 | K66: 4 | L66: 5 | M66: 12 | N66: 8 | O66: 0 | P66: 0 | Q66: 0 | R66: 0 | S66: 0 | T66: 0 | U66: 0 | V66: 4 | W66: 29 | X66: High | Y66: 0 | Z66: 0 | AA66: 46022 | AB66: 1 | AC66: 6 | AD66: 0
A67: CUST00066 | B67: 46-60 | C67: North | D67: 23 | E67: 1 | F67: 1 | G67: Savings | H67: 15 | I67: 47985.75 | J67: 3199.05 | K67: 3 | L67: 1 | M67: 13 | N67: 8 | O67: 0 | P67: 0 | Q67: 0 | R67: 0 | S67: 2 | T67: 0 | U67: 0 | V67: 4 | W67: 25 | X67: Moderate | Y67: 0 | Z67: 0 | AA67: 46011 | AB67: 12 | AC67: -3 | AD67: 1
A68: CUST00067 | B68: 36-45 | C68: Central | D68: 17 | E68: 1 | F68: 1 | G68: Savings | H68: 7 | I68: 18811.23 | J68: 2687.3185714285714 | K68: 0 | L68: 3 | M68: 14 | N68: 8 | O68: 0 | P68: 0 | Q68: 0 | R68: 0 | S68: 1 | T68: 0 | U68: 1 | V68: 3 | W68: 25 | X68: Moderate | Y68: 0 | Z68: 1 | AA68: 45983 | AB68: 40 | AC68: 5 | AD68: 0
A69: CUST00068 | B69: 26-35 | C69: North | D69: 9 | E69: 1 | F69: 1 | G69: Savings | H69: 25 | I69: 86288.81999999999 | J69: 3451.5527999999995 | K69: 4 | L69: 5 | M69: 13 | N69: 4 | O69: 0 | P69: 1 | Q69: 0 | R69: 0 | S69: 4 | T69: 2 | U69: 1 | V69: 4 | W69: 26 | X69: High | Y69: 1 | Z69: 1 | AA69: 46008 | AB69: 15 | AC69: 3 | AD69: 0
A70: CUST00069 | B70: 26-35 | C70: Central | D70: 1 | E70: 2 | F70: 2 | G70: Fixed Deposit, Savings | H70: 30 | I70: 88617.06999999999 | J70: 2953.902333333333 | K70: 3 | L70: 7 | M70: 9 | N70: 7 | O70: 0 | P70: 0 | Q70: 0 | R70: 0 | S70: 2 | T70: 0 | U70: 0 | V70: 4 | W70: 26 | X70: High | Y70: 0 | Z70: 0 | AA70: 46021 | AB70: 2 | AC70: 6 | AD70: 0
A71: CUST00070 | B71: 36-45 | C71: North | D71: 6 | E71: 2 | F71: 1 | G71: Savings | H71: 14 | I71: 34660.630000000005 | J71: 2475.759285714286 | K71: 4 | L71: 4 | M71: 9 | N71: 7 | O71: 0 | P71: 0 | Q71: 0 | R71: 0 | S71: 1 | T71: 0 | U71: 0 | V71: 4 | W71: 24 | X71: Moderate | Y71: 0 | Z71: 0 | AA71: 45978 | AB71: 45 | AC71: 0 | AD71: 0
A72: CUST00071 | B72: 60+ | C72: South | D72: 10 | E72: 2 | F72: 1 | G72: Savings | H72: 7 | I72: 7461.4 | J72: 1065.9142857142856 | K72: 1 | L72: 5 | M72: 8 | N72: 8 | O72: 0 | P72: 0 | Q72: 0 | R72: 0 | S72: 0 | T72: 0 | U72: 0 | V72: 4 | W72: 22 | X72: Moderate | Y72: 0 | Z72: 0 | AA72: 45977 | AB72: 46 | AC72: -3 | AD72: 1
A73: CUST00072 | B73: 26-35 | C73: West | D73: 9 | E73: 2 | F73: 1 | G73: Fixed Deposit | H73: 17 | I73: 44302.5 | J73: 2606.029411764706 | K73: 2 | L73: 5 | M73: 15 | N73: 5 | O73: 0 | P73: 0 | Q73: 0 | R73: 0 | S73: 2 | T73: 1 | U73: 0 | V73: 4 | W73: 27 | X73: High | Y73: 1 | Z73: 0 | AA73: 45977 | AB73: 46 | AC73: -1 | AD73: 1
A74: CUST00073 | B74: 18-25 | C74: Central | D74: 12 | E74: 1 | F74: 1 | G74: Fixed Deposit | H74: 22 | I74: 68522.68 | J74: 3114.6672727272726 | K74: 3 | L74: 5 | M74: 10 | N74: 6 | O74: 0 | P74: 0 | Q74: 0 | R74: 0 | S74: 1 | T74: 0 | U74: 1 | V74: 4 | W74: 24 | X74: High | Y74: 0 | Z74: 1 | AA74: 46002 | AB74: 21 | AC74: 0 | AD74: 0
A75: CUST00074 | B75: 26-35 | C75: Central | D75: 25 | E75: 3 | F75: 2 | G75: Salary, Savings | H75: 27 | I75: 85031.81 | J75: 3149.3262962962963 | K75: 3 | L75: 5 | M75: 13 | N75: 6 | O75: 0 | P75: 0 | Q75: 0 | R75: 0 | S75: 1 | T75: 0 | U75: 0 | V75: 4 | W75: 27 | X75: High | Y75: 0 | Z75: 0 | AA75: 46013 | AB75: 10 | AC75: -3 | AD75: 1
A76: CUST00075 | B76: 26-35 | C76: North | D76: 21 | E76: 1 | F76: 1 | G76: Savings | H76: 25 | I76: 109606.79000000001 | J76: 4384.2716 | K76: 3 | L76: 3 | M76: 6 | N76: 11 | O76: 0 | P76: 0 | Q76: 0 | R76: 0 | S76: 1 | T76: 0 | U76: 1 | V76: 4 | W76: 23 | X76: High | Y76: 0 | Z76: 1 | AA76: 46022 | AB76: 1 | AC76: 1 | AD76: 0
A77: CUST00076 | B77: 36-45 | C77: South | D77: 22 | E77: 3 | F77: 2 | G77: Current, Savings | H77: 25 | I77: 92402.95 | J77: 3696.118 | K77: 2 | L77: 4 | M77: 13 | N77: 9 | O77: 0 | P77: 0 | Q77: 0 | R77: 0 | S77: 2 | T77: 0 | U77: 1 | V77: 4 | W77: 28 | X77: High | Y77: 0 | Z77: 1 | AA77: 45961 | AB77: 62 | AC77: -5 | AD77: 1
A78: CUST00077 | B78: 36-45 | C78: North | D78: 12 | E78: 1 | F78: 1 | G78: Current | H78: 22 | I78: 70174.86 | J78: 3189.7663636363636 | K78: 5 | L78: 5 | M78: 11 | N78: 11 | O78: 0 | P78: 1 | Q78: 0 | R78: 0 | S78: 1 | T78: 1 | U78: 1 | V78: 4 | W78: 32 | X78: High | Y78: 1 | Z78: 1 | AA78: 46008 | AB78: 15 | AC78: 2 | AD78: 0
A79: CUST00078 | B79: 36-45 | C79: Central | D79: 21 | E79: 3 | F79: 3 | G79: Current, Salary, Savings | H79: 25 | I79: 88045.29000000001 | J79: 3521.8116000000005 | K79: 0 | L79: 4 | M79: 17 | N79: 8 | O79: 0 | P79: 0 | Q79: 0 | R79: 0 | S79: 1 | T79: 1 | U79: 0 | V79: 3 | W79: 29 | X79: High | Y79: 1 | Z79: 0 | AA79: 46009 | AB79: 14 | AC79: -1 | AD79: 1
A80: CUST00079 | B80: 36-45 | C80: South | D80: 25 | E80: 1 | F80: 1 | G80: Fixed Deposit | H80: 21 | I80: 106511.39 | J80: 5071.970952380952 | K80: 2 | L80: 3 | M80: 9 | N80: 6 | O80: 1 | P80: 0 | Q80: 0 | R80: 0 | S80: 0 | T80: 0 | U80: 0 | V80: 4 | W80: 20 | X80: High | Y80: 0 | Z80: 0 | AA80: 45956 | AB80: 67 | AC80: -1 | AD80: 1
A81: CUST00080 | B81: 36-45 | C81: South | D81: 15 | E81: 1 | F81: 1 | G81: Savings | H81: 18 | I81: 55847.68 | J81: 3102.648888888889 | K81: 0 | L81: 4 | M81: 15 | N81: 7 | O81: 0 | P81: 0 | Q81: 0 | R81: 0 | S81: 0 | T81: 0 | U81: 0 | V81: 3 | W81: 26 | X81: High | Y81: 0 | Z81: 0 | AA81: 46001 | AB81: 22 | AC81: 4 | AD81: 0
A82: CUST00081 | B82: 26-35 | C82: West | D82: 1 | E82: 1 | F82: 1 | G82: Current | H82: 23 | I82: 67420.88 | J82: 2931.3426086956524 | K82: 1 | L82: 4 | M82: 14 | N82: 2 | O82: 0 | P82: 0 | Q82: 0 | R82: 0 | S82: 3 | T82: 2 | U82: 1 | V82: 4 | W82: 21 | X82: High | Y82: 1 | Z82: 1 | AA82: 45996 | AB82: 27 | AC82: -5 | AD82: 1
A83: CUST00082 | B83: 46-60 | C83: South | D83: 19 | E83: 1 | F83: 1 | G83: Savings | H83: 20 | I83: 52724.63 | J83: 2636.2315 | K83: 1 | L83: 5 | M83: 7 | N83: 8 | O83: 0 | P83: 0 | Q83: 0 | R83: 0 | S83: 1 | T83: 0 | U83: 0 | V83: 4 | W83: 21 | X83: High | Y83: 0 | Z83: 0 | AA83: 45978 | AB83: 45 | AC83: -2 | AD83: 1
A84: CUST00083 | B84: 36-45 | C84: West | D84: 5 | E84: 1 | F84: 1 | G84: Fixed Deposit | H84: 16 | I84: 54272.67 | J84: 3392.0419 | K84: 0 | L84: 5 | M84: 14 | N84: 10 | O84: 0 | P84: 0 | Q84: 0 | R84: 0 | S84: 1 | T84: 1 | U84: 0 | V84: 3 | W84: 29 | X84: High | Y84: 1 | Z84: 0 | AA84: 46021 | AB84: 2 | AC84: 4 | AD84: 0
A85: CUST00084 | B85: 60+ | C85: North | D85: 13 | E85: 1 | F85: 1 | G85: Salary | H85: 11 | I85: 52807.15 | J85: 4800.650000000001 | K85: 1 | L85: 2 | M85: 12 | N85: 7 | O85: 0 | P85: 0 | Q85: 0 | R85: 0 | S85: 1 | T85: 1 | U85: 0 | V85: 4 | W85: 22 | X85: Moderate | Y85: 1 | Z85: 0 | AA85: 45964 | AB85: 59 | AC85: 5 | AD85: 0
A86: CUST00085 | B86: 36-45 | C86: South | D86: 1 | E86: 1 | F86: 1 | G86: Savings | H86: 28 | I86: 70051.01 | J86: 2501.8217857142854 | K86: 1 | L86: 8 | M86: 9 | N86: 9 | O86: 0 | P86: 0 | Q86: 0 | R86: 0 | S86: 2 | T86: 1 | U86: 0 | V86: 4 | W86: 27 | X86: High | Y86: 1 | Z86: 0 | AA86: 46015 | AB86: 8 | AC86: 6 | AD86: 0
A87: CUST00086 | B87: 60+ | C87: East | D87: 24 | E87: 1 | F87: 1 | G87: Salary | H87: 20 | I87: 54416.03 | J87: 2720.8015 | K87: 1 | L87: 6 | M87: 11 | N87: 8 | O87: 0 | P87: 0 | Q87: 0 | R87: 0 | S87: 2 | T87: 0 | U87: 1 | V87: 4 | W87: 26 | X87: High | Y87: 0 | Z87: 1 | AA87: 46022 | AB87: 1 | AC87: 8 | AD87: 0
A88: CUST00087 | B88: 26-35 | C88: East | D88: 17 | E88: 2 | F88: 2 | G88: Current, Salary | H88: 24 | I88: 91789.79000000001 | J88: 3824.5745833333335 | K88: 3 | L88: 6 | M88: 10 | N88: 7 | O88: 0 | P88: 0 | Q88: 0 | R88: 1 | S88: 0 | T88: 0 | U88: 0 | V88: 4 | W88: 26 | X88: High | Y88: 0 | Z88: 0 | AA88: 46021 | AB88: 2 | AC88: -4 | AD88: 1
A89: CUST00088 | B89: 60+ | C89: Central | D89: 13 | E89: 3 | F89: 2 | G89: Current, Fixed Deposit | H89: 11 | I89: 25035.13 | J89: 2275.9209090909094 | K89: 1 | L89: 2 | M89: 11 | N89: 10 | O89: 0 | P89: 0 | Q89: 0 | R89: 0 | S89: 0 | T89: 0 | U89: 0 | V89: 4 | W89: 24 | X89: Moderate | Y89: 0 | Z89: 0 | AA89: 46012 | AB89: 11 | AC89: 3 | AD89: 0
A90: CUST00089 | B90: 26-35 | C90: Central | D90: 7 | E90: 1 | F90: 1 | G90: Current | H90: 17 | I90: 39789.62 | J90: 2340.565882352941 | K90: 2 | L90: 6 | M90: 8 | N90: 7 | O90: 1 | P90: 0 | Q90: 0 | R90: 0 | S90: 3 | T90: 0 | U90: 0 | V90: 4 | W90: 23 | X90: High | Y90: 0 | Z90: 0 | AA90: 46016 | AB90: 7 | AC90: -1 | AD90: 1
A91: CUST00090 | B91: 46-60 | C91: West | D91: 25 | E91: 1 | F91: 1 | G91: Salary | H91: 18 | I91: 44174.85 | J91: 2454.1583333333333 | K91: 0 | L91: 4 | M91: 8 | N91: 7 | O91: 0 | P91: 0 | Q91: 0 | R91: 0 | S91: 2 | T91: 1 | U91: 2 | V91: 3 | W91: 19 | X91: High | Y91: 1 | Z91: 1 | AA91: 46003 | AB91: 20 | AC91: 6 | AD91: 0
A92: CUST00091 | B92: 18-25 | C92: Central | D92: 17 | E92: 1 | F92: 1 | G92: Savings | H92: 29 | I92: 104865.06 | J92: 3616.036551724138 | K92: 3 | L92: 6 | M92: 14 | N92: 3 | O92: 0 | P92: 0 | Q92: 0 | R92: 0 | S92: 1 | T92: 0 | U92: 0 | V92: 4 | W92: 26 | X92: High | Y92: 0 | Z92: 0 | AA92: 46022 | AB92: 1 | AC92: -5 | AD92: 1
A93: CUST00092 | B93: 46-60 | C93: North | D93: 4 | E93: 2 | F93: 1 | G93: Savings | H93: 13 | I93: 25630.1 | J93: 1971.5461538461536 | K93: 4 | L93: 6 | M93: 4 | N93: 11 | O93: 0 | P93: 0 | Q93: 0 | R93: 0 | S93: 4 | T93: 0 | U93: 0 | V93: 4 | W93: 25 | X93: Moderate | Y93: 0 | Z93: 0 | AA93: 46004 | AB93: 19 | AC93: 3 | AD93: 0
A94: CUST00093 | B94: 18-25 | C94: South | D94: 22 | E94: 1 | F94: 1 | G94: Fixed Deposit | H94: 10 | I94: 29368.08 | J94: 2936.808 | K94: 3 | L94: 5 | M94: 8 | N94: 6 | O94: 0 | P94: 0 | Q94: 0 | R94: 0 | S94: 2 | T94: 0 | U94: 0 | V94: 4 | W94: 22 | X94: Moderate | Y94: 0 | Z94: 0 | AA94: 45995 | AB94: 28 | AC94: -2 | AD94: 1
A95: CUST00094 | B95: 36-45 | C95: North | D95: 20 | E95: 1 | F95: 1 | G95: Salary | H95: 16 | I95: 35162.37 | J95: 2197.6481 | K95: 2 | L95: 5 | M95: 15 | N95: 4 | O95: 0 | P95: 0 | Q95: 0 | R95: 0 | S95: 0 | T95: 0 | U95: 0 | V95: 4 | W95: 26 | X95: High | Y95: 0 | Z95: 0 | AA95: 45970 | AB95: 53 | AC95: -2 | AD95: 1
A96: CUST00095 | B96: 46-60 | C96: South | D96: 4 | E96: 2 | F96: 2 | G96: Current, Fixed Deposit | H96: 17 | I96: 40767.67 | J96: 2398.0982352941173 | K96: 1 | L96: 4 | M96: 12 | N96: 5 | O96: 0 | P96: 0 | Q96: 0 | R96: 0 | S96: 0 | T96: 0 | U96: 0 | V96: 4 | W96: 22 | X96: High | Y96: 0 | Z96: 0 | AA96: 45995 | AB96: 28 | AC96: 5 | AD96: 0
A97: CUST00096 | B97: 46-60 | C97: South | D97: 18 | E97: 1 | F97: 1 | G97: Savings | H97: 23 | I97: 145988.58000000002 | J97: 6347.329565217392 | K97: 6 | L97: 6 | M97: 11 | N97: 9 | O97: 0 | P97: 0 | Q97: 0 | R97: 0 | S97: 0 | T97: 0 | U97: 0 | V97: 4 | W97: 32 | X97: High | Y97: 0 | Z97: 0 | AA97: 46017 | AB97: 6 | AC97: 5 | AD97: 0
A98: CUST00097 | B98: 36-45 | C98: South | D98: 6 | E98: 1 | F98: 1 | G98: Savings | H98: 16 | I98: 34931.38 | J98: 2183.2112 | K98: 0 | L98: 8 | M98: 14 | N98: 7 | O98: 0 | P98: 0 | Q98: 0 | R98: 0 | S98: 0 | T98: 0 | U98: 0 | V98: 3 | W98: 29 | X98: High | Y98: 0 | Z98: 0 | AA98: 46020 | AB98: 3 | AC98: 6 | AD98: 0
A99: CUST00098 | B99: 26-35 | C99: East | D99: 9 | E99: 1 | F99: 1 | G99: Fixed Deposit | H99: 32 | I99: 139276.41 | J99: 4352.3878 | K99: 2 | L99: 2 | M99: 8 | N99: 10 | O99: 0 | P99: 0 | Q99: 0 | R99: 0 | S99: 0 | T99: 0 | U99: 0 | V99: 4 | W99: 22 | X99: Very High | Y99: 0 | Z99: 0 | AA99: 46022 | AB99: 1 | AC99: -6 | AD99: 1
A100: CUST00099 | B100: 18-25 | C100: South | D100: 6 | E100: 1 | F100: 1 | G100: Current | H100: 17 | I100: 48994.37 | J100: 2882.0217647058826 | K100: 4 | L100: 1 | M100: 16 | N100: 6 | O100: 0 | P100: 0 | Q100: 0 | R100: 0 | S100: 1 | T100: 1 | U100: 0 | V100: 4 | W100: 27 | X100: High | Y100: 1 | Z100: 0 | AA100: 46009 | AB100: 14 | AC100: -5 | AD100: 1
...

Sheet Pivot_Analysis_2
A1: Balance Distribution by Age Band
A3: Count of account_id | B3: balance_band
A4: age_band | B4: 0-10K | C4: 100K-500K | D4: 10K-50K | E4: 500K+ | F4: 50K-100K | G4: Grand Total
A5: 18-25 | B5: 49 | C5: 58 | D5: 71 | E5: 12 | F5: 49 | G5: 239
A6: 26-35 | B6: 75 | C6: 100 | D6: 146 | E6: 37 | F6: 107 | G6: 465
A7: 36-45 | B7: 81 | C7: 89 | D7: 119 | E7: 29 | F7: 77 | G7: 395
A8: 46-60 | B8: 61 | C8: 85 | D8: 106 | E8: 33 | F8: 61 | G8: 346
A9: 60+ | B9: 32 | C9: 41 | D9: 65 | E9: 21 | F9: 37 | G9: 196
A10: Grand Total | B10: 298 | C10: 373 | D10: 507 | E10: 132 | F10: 331 | G10: 1641

Sheet Account_Data
A1: account_id | B1: customer_id | C1: account_type | D1: balance_band | E1: age_band
A2: ACC000001 | B2: CUST00001 | C2: Savings | D2: 100K-500K | E2: =VLOOKUP(B2,Customer_Data!$A:$C,2,FALSE) -> 36-45
A3: ACC000002 | B3: CUST00002 | C3: Savings | D3: 100K-500K | E3: =VLOOKUP(B3,Customer_Data!$A:$C,2,FALSE) -> 46-60
A4: ACC000003 | B4: CUST00003 | C4: Savings | D4: 500K+ | E4: =VLOOKUP(B4,Customer_Data!$A:$C,2,FALSE) -> 60+
A5: ACC000004 | B5: CUST00004 | C5: Current | D5: 10K-50K | E5: =VLOOKUP(B5,Customer_Data!$A:$C,2,FALSE) -> 60+
A6: ACC000005 | B6: CUST00005 | C6: Current | D6: 50K-100K | E6: =VLOOKUP(B6,Customer_Data!$A:$C,2,FALSE) -> 26-35
A7: ACC000006 | B7: CUST00006 | C7: Savings | D7: 0-10K | E7: =VLOOKUP(B7,Customer_Data!$A:$C,2,FALSE) -> 36-45
A8: ACC000007 | B8: CUST00006 | C8: Savings | D8: 500K+ | E8: =VLOOKUP(B8,Customer_Data!$A:$C,2,FALSE) -> 36-45
A9: ACC000008 | B9: CUST00006 | C9: Salary | D9: 50K-100K | E9: =VLOOKUP(B9,Customer_Data!$A:$C,2,FALSE) -> 36-45
A10: ACC000009 | B10: CUST00007 | C10: Salary | D10: 10K-50K | E10: =VLOOKUP(B10,Customer_Data!$A:$C,2,FALSE) -> 26-35
A11: ACC000010 | B11: CUST00008 | C11: Current | D11: 0-10K | E11: =VLOOKUP(B11,Customer_Data!$A:$C,2,FALSE) -> 46-60
A12: ACC000011 | B12: CUST00008 | C12: Fixed Deposit | D12: 100K-500K | E12: =VLOOKUP(B12,Customer_Data!$A:$C,2,FALSE) -> 46-60
A13: ACC000012 | B13: CUST00009 | C13: Savings | D13: 10K-50K | E13: =VLOOKUP(B13,Customer_Data!$A:$C,2,FALSE) -> 36-45
... A1642: ACC001641 | B1642: CUST01200 | C1642: Savings | D1642: 100K-500K | E1642: =VLOOKUP(B1642,Customer_Data!$A:$C,2,FALSE) -> 60+

Sheet Transaction_Data
A1: transaction_id | B1: customer_id | C1: account_id | D1: transaction_date | E1: amount | F1: transaction_type | G1: period
A2: TXN00000001 | B2: CUST00001 | C2: ACC000001 | D2: 45869 | E2: 3793.1 | F2: Transfer | G2: H2
A3: TXN00000002 | B3: CUST00001 | C3: ACC000001 | D3: 45778 | E3: 4284.16 | F3: Transfer | G3: H1
A4: TXN00000003 | B4: CUST00001 | C4: ACC000001 | D4: 45841 | E4: 1604.08 | F4: Transfer | G4: H2
A5: TXN00000004 | B5: CUST00001 | C5: ACC000001 | D5: 45795 | E5: 5664.84 | F5: Debit | G5: H1
A6: TXN00000005 | B6: CUST00001 | C6: ACC000001 | D6: 45942 | E6: 1740.3 | F6: Debit | G6: H2
A7: TXN00000006 | B7: CUST00001 | C7: ACC000001 | D7: 45718 | E7: 1221.64 | F7: Bill Payment | G7: H1
A8: TXN00000007 | B8: CUST00001 | C8: ACC000001 | D8: 45677 | E8: 382.15 | F8: Credit | G8: H1
A9: TXN00000008 | B9: CUST00001 | C9: ACC000001 | D9: 45694 | E9: 1129.63 | F9: Transfer | G9: H1
A10: TXN00000009 | B10: CUST00001 | C10: ACC000001 | D10: 45794 | E10: 420.82 | F10: Debit | G10: H1
A11: TXN00000010 | B11: CUST00001 | C11: ACC000001 | D11: 45787 | E11: 224.46 | F11: Credit | G11: H1
A12: TXN00000011 | B12: CUST00001 | C12: ACC000001 | D12: 45821 | E12: 608 | F12: Bill Payment | G12: H1
A13: TXN00000012 | B13: CUST00001 | C13: ACC000001 | D13: 45791 | E13: 6284.5 | F13: Credit | G13: H1
... A11425: TXN00011424 | B11425: CUST00627 | C11425: ACC000879 | D11425: 45894 | E11425: 9089.99 | F11425: Bill Payment | G11425: H2
A11426: TXN00011425 | B11426: CUST00627 | C11426: ACC000879 | D11426: 45970 | E11426: 147109.59999999998 | F11426: Credit | G11426: H2
A11427: TXN00011426 | B11427: CUST00627 | C11427: ACC000879 | D11427: 45884 | E11427: 1329.35 | F11427: Transfer | G11427: H2
A11428: TXN00011427 | B11428: CUST00627 | C11428: ACC000879 | D11428: 45926 | E11428: 6640.56 | F11428: Credit | G11428: H2
A11429: TXN00011428 | B11429: CUST00627 | C11429: ACC000879 | D11429: 45847 | E11429: 380.72 | F11429: Bill Payment | G11429: H2
A11430: TXN00011429 | B11430: CUST00627 | C11430: ACC000879 | D11430: 45782 | E11430: 22721.25 | F11430: Transfer | G11430: H1
A11431: TXN00011430 | B11431: CUST00628 | C11431: ACC000880 | D11431: 45709 | E11431: 5540.45 | F11431: Transfer | G11431: H1
A11432: TXN00011431 | B11432: CUST00628 | C11432: ACC000880 | D11432: 45670 | E11432: 272.9 | F11432: Debit | G11432: H1
A11433: TXN00011432 | B11433: CUST00628 | C11433: ACC000880 | D11433: 45974 | E11433: 3931.85 | F11433: Credit | G11433: H2
A11434: TXN00011433 | B11434: CUST00628 | C11434: ACC000880 | D11434: 45857 | E11434: 1014.38 | F11434: Bill Payment | G11434: H2
A11435: TXN00011434 | B11435: CUST00628 | C11435: ACC000880 | D11435: 45990 | E11435: 1299.41 | F11435: Bill Payment | G11435: H2
A11436: TXN00011435 | B11436: CUST00628 | C11436: ACC000880 | D11436: 45695 | E11436: 8763.15 | F11436: Bill Payment | G11436: H1
A11437: TXN00011436 | B11437: CUST00628 | C11437: ACC000880 | D11437: 45717 | E11437: 612.16 | F11437: Credit | G11437: H1
A11438: TXN00011437 | B11438: CUST00628 | C11438: ACC000880 | D11438: 45856 | E11438: 839.34 | F11438: Debit | G11438: H2
... A12878: TXN00012877 | B12878: CUST00706 | C12878: ACC000987 | D12878: 45778 | E12878: 503.95 | F12878: Credit | G12878: H1
A12879: TXN00012878 | B12879: CUST00706 | C12879: ACC000987 | D12879: 45797 | E12879: 88615.20000000001 | F12879: Transfer | G12879: H1
A12880: TXN00012879 | B12880: CUST00707 | C12880: ACC000988 | D12880: 45858 | E12880: 716.89 | F12880: Debit | G12880: H2
A12881: TXN00012880 | B12881: CUST00707 | C12881: ACC000988 | D12881: 45815 | E12881: 3190.09 | F12881: Credit | G12881: H1
A12882: TXN00012881 | B12882: CUST00707 | C12882: ACC000988 | D12882: 45719 | E12882: 3970.4 | F12882: Debit | G12882: H1
A12883: TXN00012882 | B12883: CUST00707 | C12883: ACC000988 | D12883: 45958 | E12883: 5560.12 | F12883: Transfer | G12883: H2
A12884: TXN00012883 | B12884: CUST00707 | C12884: ACC000988 | D12884: 45813 | E12884: 6007.29 | F12884: Credit | G12884: H1
A12885: TXN00012884 | B12885: CUST00707 | C12885: ACC000988 | D12885: 45942 | E12885: 1833.23 | F12885: Transfer | G12885: H2
A12886: TXN00012885 | B12886: CUST00707 | C12886: ACC000988 | D12886: 45905 | E12886: 7618.81 | F12886: Debit | G12886: H2
A12887: TXN00012886 | B12887: CUST00707 | C12887: ACC000988 | D12887: 45832 | E12887: 1669.61 | F12887: Debit | G12887: H1
A12888: TXN00012887 | B12888: CUST00707 | C12888: ACC000988 | D12888: 45808 | E12888: 607.89 | F12888: Debit | G12888: H1
A12889: TXN00012888 | B12889: CUST00707 | C12889: ACC000988 | D12889: 45887 | E12889: 602.94 | F12889: Credit | G12889: H2
A12890: TXN00012889 | B12890: CUST00707 | C12890: ACC000988 | D12890: 45795 | E12890: 365.3 | F12890: Debit | G12890: H1
A12891: TXN00012890 | B12891: CUST00707 | C12891: ACC000988 | D12891: 45758 | E12891: 1202.03 | F12891: Cash Withdrawal | G12891: H1
... A14518: TXN00014517 | B14518: CUST00797 | C14518: ACC001106 | D14518: 45766 | E14518: 992.44 | F14518: Credit | G14518: H1
A14519: TXN00014518 | B14519: CUST00798 | C14519: ACC001107 | D14519: 45931 | E14519: 134449.59999999998 | F14519: Debit | G14519: H2
A14520: TXN00014519 | B14520: CUST00798 | C14520: ACC001107 | D14520: 45683 | E14520: 5355.69 | F14520: Credit | G14520: H1
A14521: TXN00014520 | B14521: CUST00798 | C14521: ACC001107 | D14521: 45778 | E14521: 281.88 | F14521: Cash Withdrawal | G14521: H1
A14522: TXN00014521 | B14522: CUST00798 | C14522: ACC001107 | D14522: 45833 | E14522: 3522.28 | F14522: Debit | G14522: H1
A14523: TXN00014522 | B14523: CUST00798 | C14523: ACC001107 | D14523: 45732 | E14523: 1443.9 | F14523: Credit | G14523: H1
A14524: TXN00014523 | B14524: CUST00798 | C14524: ACC001107 | D14524: 45843 | E14524: 1788.41 | F14524: Bill Payment | G14524: H2
A14525: TXN00014524 | B14525: CUST00799 | C14525: ACC001108 | D14525: 45972 | E14525: 6058.63 | F14525: Debit | G14525: H2
A14526: TXN00014525 | B14526: CUST00799 | C14526: ACC001108 | D14526: 45930 | E14526: 5615.62 | F14526: Credit | G14526: H2
A14527: TXN00014526 | B14527: CUST00799 | C14527: ACC001108 | D14527: 45937 | E14527: 2103.17 | F14527: Debit | G14527: H2
A14528: TXN00014527 | B14528: CUST00799 | C14528: ACC001108 | D14528: 45777 | E14528: 1973.82 | F14528: Credit | G14528: H1
A14529: TXN00014528 | B14529: CUST00799 | C14529: ACC001108 | D14529: 45918 | E14529: 8380.89 | F14529: Transfer | G14529: H2
A14530: TXN00014529 | B14530: CUST00799 | C14530: ACC001108 | D14530: 45729 | E14530: 3183.25 | F14530: Debit | G14530: H1
A14531: TXN00014530 | B14531: CUST00799 | C14531: ACC001108 | D14531: 45837 | E14531: 1679.91 | F14531: Debit | G14531: H1
... A20110: TXN00020109 | B20110: CUST01103 | C20110: ACC001516 | D20110: 45688 | E20110: 2315.83 | F20110: Debit | G20110: H1
A20111: TXN00020110 | B20111: CUST01103 | C20111: ACC001516 | D20111: 45855 | E20111: 35397.600000000006 | F20111: Bill Payment | G20111: H2
A20112: TXN00020111 | B20112: CUST01103 | C20112: ACC001516 | D20112: 45939 | E20112: 1585.62 | F20112: Debit | G20112: H2
A20113: TXN00020112 | B20113: CUST01103 | C20113: ACC001516 | D20113: 45881 | E20113: 812.54 | F20113: Credit | G20113: H2
A20114: TXN00020113 | B20114: CUST01103 | C20114: ACC001516 | D20114: 45837 | E20114: 863.08 | F20114: Bill Payment | G20114: H1
A20115: TXN00020114 | B20115: CUST01103 | C20115: ACC001516 | D20115: 45935 | E20115: 1598.07 | F20115: Debit | G20115: H2
A20116: TXN00020115 | B20116: CUST01103 | C20116: ACC001516 | D20116: 46020 | E20116: 669.07 | F20116: Debit | G20116: H2
A20117: TXN00020116 | B20117: CUST01103 | C20117: ACC001516 | D20117: 45962 | E20117: 1952.71 | F20117: Cash Withdrawal | G20117: H2
A20118: TXN00020117 | B20118: CUST01103 | C20118: ACC001516 | D20118: 45818 | E20118: 376.76 | F20118: Credit | G20118: H1
A20119: TXN00020118 | B20119: CUST01103 | C20119: ACC001516 | D20119: 45805 | E20119: 1300.49 | F20119: Credit | G20119: H1
A20120: TXN00020119 | B20120: CUST01103 | C20120: ACC001516 | D20120: 45723 | E20120: 771.37 | F20120: Debit | G20120: H1
A20121: TXN00020120 | B20121: CUST01103 | C20121: ACC001516 | D20121: 45658 | E20121: 7724.59 | F20121: Transfer | G20121: H1
A20122: TXN00020121 | B20122: CUST01103 | C20122: ACC001516 | D20122: 45790 | E20122: 1117.08 | F20122: Credit | G20122: H1
A20123: TXN00020122 | B20123: CUST01103 | C20123: ACC001516 | D20123: 45710 | E20123: 16600.84 | F20123: Credit | G20123: H1
... A21824: TXN00021823 | B21824: CUST01200 | C21824: ACC001641 | D21824: 45782 | E21824: 3034.34 | F21824: Credit | G21824: H1

Sheet Pivot_Analysis_1
A1: Complaint Analysis by Region
A3: Count of service_id | B3: complaint_flag
A4: region | B4: No | C4: Unknown | D4: Yes | E4: Grand Total
A5: Central | B5: 153 | C5: 18 | D5: 67 | E5: 238
A6: East | B6: 158 | C6: 12 | D6: 71 | E6: 241
A7: North | B7: 156 | C7: 18 | D7: 64 | E7: 238
A8: South | B8: 201 | C8: 22 | D8: 89 | E8: 312
A9: West | B9: 221 | C9: 24 | D9: 82 | E9: 327
A10: Grand Total | B10: 889 | C10: 94 | D10: 373 | E10: 1356
A32: Service Request Trends
A35: request_type | B35: Count of service_id
A36: Account Update | B36: 211
A37: Card Issue | B37: 227
A38: Digital Banking | B38: 224
A39: Loan Query | B39: 229
A40: Other | B40: 229
A41: Transaction Dispute | B41: 236
A42: Grand Total | B42: 1356

Sheet Service_Data
A1: service_id | B1: customer_id | C1: request_type | D1: complaint_flag | E1: resolution | F1: service_date | G1: is_complaint | H1: is_unresolved | I1: region
A2: SRV0000001 | B2: CUST00001 | C2: Loan Query | D2: No | E2: Resolved | F2: 46001 | G2: 0 | H2: 0 | I2: =VLOOKUP(B2,Customer_Data!$A:$C,3,FALSE) -> South
A3: SRV0000002 | B3: CUST00002 | C3: Account Update | D3: No | E3: Resolved | F3: 45822 | G3: 0 | H3: 0 | I3: =VLOOKUP(B2,Customer_Data!$A:$C,3,FALSE) -> South
A4: SRV0000003 | B4: CUST00003 | C4: Card Issue | D4: Yes | E4: Resolved | F4: 45727 | G4: 1 | H4: 0 | I4: =VLOOKUP(B2,Customer_Data!$A:$C,3,FALSE) -> South
A5: SRV0000004 | B5: CUST00004 | C5: Loan Query | D5: Yes | E5: Resolved | F5: 45825 | G5: 1 | H5: 0 | I5: =VLOOKUP(B2,Customer_Data!$A:$C,3,FALSE) -> South
A6: SRV0000005 | B6: CUST00004 | C6: Transaction Dispute | D6: No | E6: Resolved | F6: 45760 | G6: 0 | H6: 0 | I6: =VLOOKUP(B2,Customer_Data!$A:$C,3,FALSE) -> South
A7: SRV0000006 | B7: CUST00005 | C7: Account Update | D7: No | E7: Resolved | F7: 45723 | G7: 0 | H7: 0 | I7: =VLOOKUP(B2,Customer_Data!$A:$C,3,FALSE) -> South
A8: SRV0000007 | B8: CUST00006 | C8: Other | D8: Yes | E8: Resolved | F8: 45939 | G8: 1 | H8: 0 | I8: =VLOOKUP(B3,Customer_Data!$A:$C,3,FALSE) -> West
A9: SRV0000008 | B9: CUST00006 | C9: Other | D9: Yes | E9: Resolved | F9: 45966 | G9: 1 | H9: 0 | I9: =VLOOKUP(B4,Customer_Data!$A:$C,3,FALSE) -> Central
A10: SRV0000009 | B10: CUST00008 | C10: Account Update | D10: No | E10: Resolved | F10: 45929 | G10: 0 | H10: 0 | I10: =VLOOKUP(B5,Customer_Data!$A:$C,3,FALSE) -> West
A11: SRV0000010 | B11: CUST00010 | C11: Digital Banking | D11: Yes | E11: Resolved | F11: 45828 | G11: 1 | H11: 0 | I11: =VLOOKUP(B6,Customer_Data!$A:$C,3,FALSE) -> West
A12: SRV0000011 | B12: CUST00010 | C12: Card Issue | D12: No | E12: Resolved | F12: 45938 | G12: 0 | H12: 0 | I12: =VLOOKUP(B7,Customer_Data!$A:$C,3,FALSE) -> West
A13: SRV0000012 | B13: CUST00012 | C13: Digital Banking | D13: No | E13: Resolved | F13: 45701 | G13: 0 | H13: 0 | I13: =VLOOKUP(B8,Customer_Data!$A:$C,3,FALSE) -> East
A14: SRV0000013 | B14: CUST00013 | C14: Digital Banking | D14: No | E14: Resolved | F14: 45813 | G14: 0 | H14: 0 | I14: =VLOOKUP(B9,Customer_Data!$A:$C,3,FALSE) -> East
A15: SRV0000014 | B15: CUST00014 | C15: Transaction Dispute | D15: Unknown | E15: Resolved | F15: 45662 | G15: 0 | H15: 0 | I15: =VLOOKUP(B10,Customer_Data!$A:$C,3,FALSE) -> West
A16: SRV0000015 | B16: CUST00016 | C16: Loan Query | D16: No | E16: Resolved | F16: 45705 | G16: 0 | H16: 0 | I16: =VLOOKUP(B11,Customer_Data!$A:$C,3,FALSE) -> South
A17: SRV0000016 | B17: CUST00016 | C17: Transaction Dispute | D17: No | E17: Resolved | F17: 45806 | G17: 0 | H17: 0 | I17: =VLOOKUP(B12,Customer_Data!$A:$C,3,FALSE) -> South
A18: SRV0000017 | B18: CUST00017 | C18: Loan Query | D18: Yes | E18: Pending | F18: 45831 | G18: 1 | H18: 1 | I18: =VLOOKUP(B13,Customer_Data!$A:$C,3,FALSE) -> Central
... A1357: SRV0001356 | B1357: CUST01197 | C1357: Transaction Dispute | D1357: No | E1357: Resolved | F1357: 45945 | G1357: 0 | H1357: 0 | I1357: =VLOOKUP(B1352,Customer_Data!$A:$C,3,FALSE) -> West

Sheet summary
A2: Channel | B2: Total Usage
A3: Branch Visits | B3: =SUM(Customer_Data!K2:K1201) -> 2635
A4: Atm Usage | B4: =SUM(Customer_Data!L2:L1201) -> 5948
A5: Mobile Usage | B5: =SUM(Customer_Data!M2:M1201) -> 13012
A6: Internet Usage | B6: =SUM(Customer_Data!N2:N1201) -> 8369
